pineconeutils/__init__.py
pineconeutils/cohere_embedding.py
pineconeutils/cohere_services.py
pineconeutils/docx_handler.py
pineconeutils/openai_embedding.py
pineconeutils/openai_services.py
pineconeutils/pdf_handler.py
pineconeutils/pinecone_services.py
pineconeutils/text_handler.py
pineconeutils/utils.py
pineconeutils-0.0.4.dist-info/METADATA
pineconeutils-0.0.4.dist-info/WHEEL
pineconeutils-0.0.4.dist-info/top_level.txt
pineconeutils-0.0.4.dist-info/RECORD
